small_gicp.cpython-39-x86_64-linux-gnu.so
small_gicp-1.0.0.dist-info/RECORD
small_gicp-1.0.0.dist-info/WHEEL
small_gicp-1.0.0.dist-info/METADATA
small_gicp-1.0.0.dist-info/licenses/LICENSE
small_gicp.libs/libgomp-a97153a2.so.1.0.0
