Metadata-Version: 2.1
Name: small_gicp
Version: 1.0.0
Summary: Efficient and parallelized algorithms for fine point cloud registration
Author-Email: Kenji Koide <k.koide@aist.go.jp>
License: MIT
Project-URL: Homepage, https://github.com/koide3/small_gicp
Requires-Python: >=3.7
